pydbc/parser/__init__.py
pydbc/parser/exception.py
pydbc/parser/lexer.py
pydbc/parser/node.py
pydbc/parser/parsetab.py
pydbc/parser/scanner.py
sauci_pydbc-0.1.2.dist-info/LICENSE.md
sauci_pydbc-0.1.2.dist-info/METADATA
sauci_pydbc-0.1.2.dist-info/WHEEL
sauci_pydbc-0.1.2.dist-info/top_level.txt
sauci_pydbc-0.1.2.dist-info/RECORD
