Metadata-Version: 2.1
Name: sauci-pydbc
Version: 0.1.2
Summary: utility for dbc files
Home-page: https://github.com/Sauci/pydbc
Author: Guillaume Sottas
Author-email: guillaume.sottas@liebherr.com
License: BSD
Platform: UNKNOWN
Requires-Dist: ply
